twquant/__init__.py
twquant/drv.py
twquant/gen.py
twquant/stockindc.py
twquant-0.0.1.dist-info/LICENSE.txt
twquant-0.0.1.dist-info/METADATA
twquant-0.0.1.dist-info/WHEEL
twquant-0.0.1.dist-info/top_level.txt
twquant-0.0.1.dist-info/RECORD
