Metadata-Version: 2.1
Name: twquant
Version: 0.0.1
Summary: retrieve financial-related data and use the data on investment decision making
Home-page: https://github.com/gary136/twquant
Author: Gary
Author-email: sarcas0705@gmail.com
License: MIT
Keywords: SOME,MEANINGFULL,KEYWORDS
Platform: UNKNOWN
Classifier: Programming Language :: Python :: 3
Classifier: License :: OSI Approved :: MIT License
Classifier: Operating System :: OS Independent
Requires-Python: >=3.6
